json_and_html/__init__.py
json_and_html/json_and_html_core.py
json_and_html-1.0.1.dist-info/LICENSE
json_and_html-1.0.1.dist-info/METADATA
json_and_html-1.0.1.dist-info/WHEEL
json_and_html-1.0.1.dist-info/top_level.txt
json_and_html-1.0.1.dist-info/RECORD
