Metadata-Version: 2.1
Name: json-and-html
Version: 1.0.1
Summary: A lightweight solution to converting JSON files into HTML tables, in Python
Home-page: https://github.com/Whoeza/json_and_html
Author: Whoeza
License: GNU GPLv3
Project-URL: Bug Tracker, https://github.com/Whoeza/json_and_html/issues
Classifier: Intended Audience :: Developers
Classifier: License :: OSI Approved :: GNU General Public License v3 (GPLv3)
Classifier: Operating System :: OS Independent
Classifier: Programming Language :: ML
Classifier: Programming Language :: Python :: 3
Classifier: Topic :: Software Development :: Code Generators
Classifier: Topic :: Text Processing :: Markup :: HTML
Requires-Python: >=3.6
License-File: LICENSE
Requires-Dist: dict-and-html (>=1.0.11)
